agentlightning/__init__.py
agentlightning/client.py
agentlightning/config.py
agentlightning/llm_proxy.py
agentlightning/logging.py
agentlightning/reward.py
agentlightning/server.py
agentlightning/adapter/__init__.py
agentlightning/adapter/base.py
agentlightning/adapter/messages.py
agentlightning/adapter/triplet.py
agentlightning/algorithm/__init__.py
agentlightning/algorithm/base.py
agentlightning/algorithm/decorator.py
agentlightning/algorithm/fast.py
agentlightning/algorithm/apo/__init__.py
agentlightning/algorithm/apo/apo.py
agentlightning/algorithm/apo/prompts/apply_edit_variant01.poml
agentlightning/algorithm/apo/prompts/apply_edit_variant02.poml
agentlightning/algorithm/apo/prompts/text_gradient_variant01.poml
agentlightning/algorithm/apo/prompts/text_gradient_variant02.poml
agentlightning/algorithm/apo/prompts/text_gradient_variant03.poml
agentlightning/algorithm/verl/__init__.py
agentlightning/algorithm/verl/interface.py
agentlightning/cli/__init__.py
agentlightning/cli/agentops_server.py
agentlightning/cli/store.py
agentlightning/cli/vllm.py
agentlightning/emitter/__init__.py
agentlightning/emitter/exception.py
agentlightning/emitter/message.py
agentlightning/emitter/object.py
agentlightning/emitter/reward.py
agentlightning/emitter/utils.py
agentlightning/execution/__init__.py
agentlightning/execution/base.py
agentlightning/execution/client_server.py
agentlightning/execution/events.py
agentlightning/execution/inter_process.py
agentlightning/execution/shared_memory.py
agentlightning/instrumentation/__init__.py
agentlightning/instrumentation/agentops.py
agentlightning/instrumentation/agentops_langchain.py
agentlightning/instrumentation/litellm.py
agentlightning/instrumentation/vllm.py
agentlightning/litagent/__init__.py
agentlightning/litagent/decorator.py
agentlightning/litagent/litagent.py
agentlightning/runner/__init__.py
agentlightning/runner/agent.py
agentlightning/runner/base.py
agentlightning/runner/legacy.py
agentlightning/store/__init__.py
agentlightning-0.2.2.dist-info/METADATA
agentlightning-0.2.2.dist-info/WHEEL
agentlightning-0.2.2.dist-info/entry_points.txt
agentlightning-0.2.2.dist-info/licenses/LICENSE
agentlightning-0.2.2.dist-info/RECORD
