Metadata-Version: 2.4
Name: agentlightning
Version: 0.2.2
Summary: Agent-lightning is the absolute trainer to light up AI agents.
License-File: LICENSE
Requires-Python: >=3.10
Requires-Dist: agentops>=0.4.13
Requires-Dist: aiohttp
Requires-Dist: fastapi
Requires-Dist: flask
Requires-Dist: graphviz
Requires-Dist: httpdbg
Requires-Dist: litellm[proxy]>=1.74
Requires-Dist: openai
Requires-Dist: opentelemetry-api>=1.35
Requires-Dist: opentelemetry-exporter-otlp>=1.35
Requires-Dist: opentelemetry-sdk>=1.35
Requires-Dist: psutil
Requires-Dist: pydantic>=2.11
Requires-Dist: rich
Requires-Dist: setproctitle
Requires-Dist: uvicorn
Provides-Extra: apo
Requires-Dist: poml; extra == 'apo'
Provides-Extra: verl
Requires-Dist: verl>=0.5.0; extra == 'verl'
Requires-Dist: vllm<0.11.0,>=0.8.4; extra == 'verl'
